{"name":"Acre","region":"HaZafon","country":"Israel","lat":32.9236,"lon":35.0728,"tz_id":"Asia/Jerusalem","localtime_epoch":1734309981,"localtime":"2024-12-16 02:46","last_updated_epoch":1734309900,"last_updated":"2024-12-16 02:45","temp_c":13.6,"temp_f":56.5,"is_day":0,"wind_mph":8.7,"wind_kph":14,"wind_degree":108,"wind_dir":"ESE","pressure_mb":1025,"pressure_in":30.26,"precip_mm":0,"precip_in":0,"humidity":32,"cloud":0,"feelslike_c":12.5,"feelslike_f":54.4,"windchill_c":12.5,"windchill_f":54.4,"heatindex_c":13.6,"heatindex_f":56.5,"dewpoint_c":-2.7,"dewpoint_f":27.2,"vis_km":10,"vis_miles":6,"uv":0,"gust_mph":15.2,"gust_kph":24.5,"text":"Clear","icon":"//cdn.weatherapi.com/weather/64x64/night/113.png","code":1000}