{"name":"Acre","region":"HaZafon","country":"Israel","lat":32.92,"lon":35.07,"tz_id":"Asia/Jerusalem","localtime_epoch":1680137874,"localtime":"2023-03-30 3:57","last_updated_epoch":1680137100,"last_updated":"2023-03-30 03:45","temp_c":13.7,"temp_f":56.7,"is_day":0,"wind_mph":15.7,"wind_kph":25.2,"wind_degree":261,"wind_dir":"W","pressure_mb":1018,"pressure_in":30.05,"precip_mm":0,"precip_in":0,"humidity":57,"cloud":81,"feelslike_c":11.7,"feelslike_f":53.1,"vis_km":10,"vis_miles":6,"uv":1,"gust_mph":19.9,"gust_kph":32,"text":"Cloudy","icon":"//cdn.weatherapi.com/weather/64x64/night/119.png","code":1006}