{"name":"Acre","region":"HaZafon","country":"Israel","lat":32.92,"lon":35.07,"tz_id":"Asia/Jerusalem","localtime_epoch":1673830612,"localtime":"2023-01-16 2:56","last_updated_epoch":1673829900,"last_updated":"2023-01-16 02:45","temp_c":13.4,"temp_f":56.1,"is_day":0,"wind_mph":7.4,"wind_kph":11.9,"wind_degree":150,"wind_dir":"SSE","pressure_mb":1018,"pressure_in":30.06,"precip_mm":0,"precip_in":0,"humidity":74,"cloud":53,"feelslike_c":12.4,"feelslike_f":54.3,"vis_km":10,"vis_miles":6,"uv":1,"gust_mph":11.4,"gust_kph":18.4,"text":"Partly cloudy","icon":"//cdn.weatherapi.com/weather/64x64/night/116.png","code":1003}