{"name":"`Afula","region":"HaZafon","country":"Israel","lat":32.61,"lon":35.29,"tz_id":"Asia/Jerusalem","localtime_epoch":1719363175,"localtime":"2024-06-26 3:52","last_updated_epoch":1719362700,"last_updated":"2024-06-26 03:45","temp_c":21.9,"temp_f":71.5,"is_day":0,"wind_mph":4.5,"wind_kph":7.2,"wind_degree":256,"wind_dir":"WSW","pressure_mb":1006,"pressure_in":29.7,"precip_mm":0,"precip_in":0,"humidity":91,"cloud":6,"feelslike_c":21.9,"feelslike_f":71.5,"windchill_c":21.9,"windchill_f":71.5,"heatindex_c":24.5,"heatindex_f":76.1,"dewpoint_c":20.4,"dewpoint_f":68.8,"vis_km":10,"vis_miles":6,"uv":1,"gust_mph":7.7,"gust_kph":12.3,"text":"Clear","icon":"//cdn.weatherapi.com/weather/64x64/night/113.png","code":1000}