{"name":"`Arad","region":"HaDarom","country":"Israel","lat":31.25,"lon":35.2167,"tz_id":"Asia/Jerusalem","localtime_epoch":1738803797,"localtime":"2025-02-06 03:03","last_updated_epoch":1738803600,"last_updated":"2025-02-06 03:00","temp_c":12.5,"temp_f":54.6,"is_day":0,"wind_mph":22.6,"wind_kph":36.4,"wind_degree":245,"wind_dir":"WSW","pressure_mb":1011,"pressure_in":29.87,"precip_mm":0.06,"precip_in":0,"humidity":54,"cloud":76,"feelslike_c":9.6,"feelslike_f":49.2,"windchill_c":9.6,"windchill_f":49.2,"heatindex_c":12.6,"heatindex_f":54.6,"dewpoint_c":3.6,"dewpoint_f":38.5,"vis_km":10,"vis_miles":6,"uv":0,"gust_mph":31.7,"gust_kph":51,"text":"Patchy rain nearby","icon":"//cdn.weatherapi.com/weather/64x64/night/176.png","code":1063}