{"name":"`Arad","region":"HaDarom","country":"Israel","lat":31.25,"lon":35.2167,"tz_id":"Asia/Jerusalem","localtime_epoch":1730596086,"localtime":"2024-11-03 03:08","last_updated_epoch":1730595600,"last_updated":"2024-11-03 03:00","temp_c":20.9,"temp_f":69.6,"is_day":0,"wind_mph":2.7,"wind_kph":4.3,"wind_degree":279,"wind_dir":"W","pressure_mb":1014,"pressure_in":29.96,"precip_mm":0.09,"precip_in":0,"humidity":61,"cloud":84,"feelslike_c":20.9,"feelslike_f":69.6,"windchill_c":20.9,"windchill_f":69.6,"heatindex_c":20.9,"heatindex_f":69.6,"dewpoint_c":13.1,"dewpoint_f":55.6,"vis_km":10,"vis_miles":6,"uv":0,"gust_mph":4.4,"gust_kph":7,"text":"Patchy rain nearby","icon":"//cdn.weatherapi.com/weather/64x64/night/176.png","code":1063}