{"name":"`Arraba","region":"HaZafon","country":"Israel","lat":32.85,"lon":35.34,"tz_id":"Asia/Jerusalem","localtime_epoch":1684112246,"localtime":"2023-05-15 3:57","last_updated_epoch":1684111500,"last_updated":"2023-05-15 03:45","temp_c":15.3,"temp_f":59.5,"is_day":0,"wind_mph":2.2,"wind_kph":3.6,"wind_degree":253,"wind_dir":"WSW","pressure_mb":1013,"pressure_in":29.9,"precip_mm":0,"precip_in":0,"humidity":78,"cloud":16,"feelslike_c":15.3,"feelslike_f":59.5,"vis_km":10,"vis_miles":6,"uv":1,"gust_mph":4.3,"gust_kph":6.8,"text":"Clear","icon":"//cdn.weatherapi.com/weather/64x64/night/113.png","code":1000}