{"name":"`Arraba","region":"HaZafon","country":"Israel","lat":32.8486,"lon":35.3358,"tz_id":"Asia/Jerusalem","localtime_epoch":1733100996,"localtime":"2024-12-02 02:56","last_updated_epoch":1733100300,"last_updated":"2024-12-02 02:45","temp_c":10.2,"temp_f":50.3,"is_day":0,"wind_mph":2.2,"wind_kph":3.6,"wind_degree":11,"wind_dir":"NNE","pressure_mb":1019,"pressure_in":30.1,"precip_mm":0,"precip_in":0,"humidity":52,"cloud":33,"feelslike_c":10.2,"feelslike_f":50.3,"windchill_c":10.2,"windchill_f":50.3,"heatindex_c":10.2,"heatindex_f":50.3,"dewpoint_c":0.9,"dewpoint_f":33.7,"vis_km":10,"vis_miles":6,"uv":0,"gust_mph":2.8,"gust_kph":4.5,"text":"Partly Cloudy","icon":"//cdn.weatherapi.com/weather/64x64/night/116.png","code":1003}