{"name":"Beersheba","region":"HaDarom","country":"Israel","lat":31.23,"lon":34.78,"tz_id":"Asia/Jerusalem","localtime_epoch":1681260940,"localtime":"2023-04-12 3:55","last_updated_epoch":1681260300,"last_updated":"2023-04-12 03:45","temp_c":13.5,"temp_f":56.3,"is_day":0,"wind_mph":10.3,"wind_kph":16.6,"wind_degree":307,"wind_dir":"NW","pressure_mb":1009,"pressure_in":29.79,"precip_mm":1,"precip_in":0.04,"humidity":72,"cloud":98,"feelslike_c":12.1,"feelslike_f":53.8,"vis_km":9,"vis_miles":5,"uv":1,"gust_mph":13.4,"gust_kph":21.6,"text":"Light rain","icon":"//cdn.weatherapi.com/weather/64x64/night/296.png","code":1183}