{"name":"Beit-Shemesh","region":"Yerushalayim","country":"Israel","lat":31.75,"lon":35,"tz_id":"Asia/Jerusalem","localtime_epoch":1724979702,"localtime":"2024-08-30 04:01","last_updated_epoch":1724978700,"last_updated":"2024-08-30 03:45","temp_c":20.9,"temp_f":69.6,"is_day":0,"wind_mph":8.3,"wind_kph":13.3,"wind_degree":286,"wind_dir":"WNW","pressure_mb":1012,"pressure_in":29.88,"precip_mm":0.01,"precip_in":0,"humidity":78,"cloud":76,"feelslike_c":20.9,"feelslike_f":69.6,"windchill_c":20.9,"windchill_f":69.6,"heatindex_c":20.9,"heatindex_f":69.6,"dewpoint_c":17,"dewpoint_f":62.6,"vis_km":10,"vis_miles":6,"uv":1,"gust_mph":14,"gust_kph":22.5,"text":"Patchy rain nearby","icon":"//cdn.weatherapi.com/weather/64x64/night/176.png","code":1063}