{"name":"Beit-Shemesh","region":"Yerushalayim","country":"Israel","lat":31.75,"lon":35,"tz_id":"Asia/Jerusalem","localtime_epoch":1735261545,"localtime":"2024-12-27 03:05","last_updated_epoch":1735261200,"last_updated":"2024-12-27 03:00","temp_c":10.9,"temp_f":51.6,"is_day":0,"wind_mph":5.6,"wind_kph":9,"wind_degree":212,"wind_dir":"SSW","pressure_mb":1016,"pressure_in":30,"precip_mm":0,"precip_in":0,"humidity":60,"cloud":4,"feelslike_c":9.9,"feelslike_f":49.8,"windchill_c":9.9,"windchill_f":49.8,"heatindex_c":10.9,"heatindex_f":51.6,"dewpoint_c":3.4,"dewpoint_f":38.1,"vis_km":10,"vis_miles":6,"uv":0,"gust_mph":8.6,"gust_kph":13.9,"text":"Clear","icon":"//cdn.weatherapi.com/weather/64x64/night/113.png","code":1000}