{"name":"Beit Shean","region":"HaZafon","country":"Israel","lat":32.5,"lon":35.5,"tz_id":"Asia/Jerusalem","localtime_epoch":1657860873,"localtime":"2022-07-15 7:54","last_updated_epoch":1657860300,"last_updated":"2022-07-15 07:45","temp_c":25.1,"temp_f":77.2,"is_day":1,"wind_mph":6,"wind_kph":9.7,"wind_degree":232,"wind_dir":"SW","pressure_mb":1006,"pressure_in":29.71,"precip_mm":0,"precip_in":0,"humidity":77,"cloud":64,"feelslike_c":27.1,"feelslike_f":80.8,"vis_km":10,"vis_miles":6,"uv":6,"gust_mph":6.9,"gust_kph":11.2,"text":"Cloudy","icon":"//cdn.weatherapi.com/weather/64x64/day/119.png","code":1006}