{"name":"Beit Shean","region":"HaZafon","country":"Israel","lat":32.5,"lon":35.5,"tz_id":"Asia/Jerusalem","localtime_epoch":1729645508,"localtime":"2024-10-23 04:05","last_updated_epoch":1729645200,"last_updated":"2024-10-23 04:00","temp_c":17.2,"temp_f":62.9,"is_day":0,"wind_mph":5.1,"wind_kph":8.3,"wind_degree":57,"wind_dir":"ENE","pressure_mb":1019,"pressure_in":30.09,"precip_mm":0,"precip_in":0,"humidity":27,"cloud":0,"feelslike_c":17.2,"feelslike_f":62.9,"windchill_c":17.2,"windchill_f":62.9,"heatindex_c":17.2,"heatindex_f":62.9,"dewpoint_c":-1.9,"dewpoint_f":28.5,"vis_km":10,"vis_miles":6,"uv":0,"gust_mph":8.3,"gust_kph":13.3,"text":"Clear","icon":"//cdn.weatherapi.com/weather/64x64/night/113.png","code":1000}