{"name":"Brak","region":"Central Java","country":"Indonesia","lat":-7.18,"lon":108.8,"tz_id":"Asia/Jakarta","localtime_epoch":1709340444,"localtime":"2024-03-02 7:47","last_updated_epoch":1709340300,"last_updated":"2024-03-02 07:45","temp_c":23.6,"temp_f":74.5,"is_day":1,"wind_mph":2.2,"wind_kph":3.6,"wind_degree":248,"wind_dir":"WSW","pressure_mb":1010,"pressure_in":29.81,"precip_mm":0,"precip_in":0,"humidity":92,"cloud":27,"feelslike_c":25.9,"feelslike_f":78.7,"vis_km":10,"vis_miles":6,"uv":7,"gust_mph":6.7,"gust_kph":10.8,"text":"Partly Cloudy ","icon":"//cdn.weatherapi.com/weather/64x64/day/116.png","code":1003}