{"name":"Dimona","region":"HaDarom","country":"Israel","lat":31.0667,"lon":35.0333,"tz_id":"Asia/Jerusalem","localtime_epoch":1740877957,"localtime":"2025-03-02 03:12","last_updated_epoch":1740877200,"last_updated":"2025-03-02 03:00","temp_c":13.3,"temp_f":55.9,"is_day":0,"wind_mph":2.2,"wind_kph":3.6,"wind_degree":352,"wind_dir":"N","pressure_mb":1023,"pressure_in":30.2,"precip_mm":0,"precip_in":0,"humidity":70,"cloud":1,"feelslike_c":14,"feelslike_f":57.2,"windchill_c":14,"windchill_f":57.2,"heatindex_c":13.3,"heatindex_f":55.9,"dewpoint_c":7.9,"dewpoint_f":46.2,"vis_km":10,"vis_miles":6,"uv":0,"gust_mph":3.5,"gust_kph":5.6,"text":"Clear","icon":"//cdn.weatherapi.com/weather/64x64/night/113.png","code":1000}