{"name":"Eilat","region":"HaDarom","country":"Israel","lat":29.56,"lon":34.95,"tz_id":"Asia/Amman","localtime_epoch":1709772043,"localtime":"2024-03-07 3:40","last_updated_epoch":1709771400,"last_updated":"2024-03-07 03:30","temp_c":17,"temp_f":62.6,"is_day":0,"wind_mph":6.9,"wind_kph":11.2,"wind_degree":360,"wind_dir":"N","pressure_mb":1017,"pressure_in":30.03,"precip_mm":0,"precip_in":0,"humidity":42,"cloud":0,"feelslike_c":17,"feelslike_f":62.6,"vis_km":7,"vis_miles":4,"uv":1,"gust_mph":12.4,"gust_kph":19.9,"text":"Clear","icon":"//cdn.weatherapi.com/weather/64x64/night/113.png","code":1000}