{"name":"Eilat","region":"HaDarom","country":"Israel","lat":29.5611,"lon":34.9517,"tz_id":"Asia/Amman","localtime_epoch":1736816565,"localtime":"2025-01-14 04:02","last_updated_epoch":1736816400,"last_updated":"2025-01-14 04:00","temp_c":13.8,"temp_f":56.8,"is_day":0,"wind_mph":4.9,"wind_kph":7.9,"wind_degree":45,"wind_dir":"NE","pressure_mb":1020,"pressure_in":30.13,"precip_mm":0,"precip_in":0,"humidity":38,"cloud":0,"feelslike_c":13.5,"feelslike_f":56.3,"windchill_c":13.5,"windchill_f":56.3,"heatindex_c":13.8,"heatindex_f":56.8,"dewpoint_c":-0.2,"dewpoint_f":31.6,"vis_km":10,"vis_miles":6,"uv":0,"gust_mph":10.3,"gust_kph":16.6,"text":"Clear","icon":"//cdn.weatherapi.com/weather/64x64/night/113.png","code":1000}