{"name":"Agudat Israel","region":"HaDarom","country":"Israel","lat":31.75,"lon":34.7833,"tz_id":"Asia/Jerusalem","localtime_epoch":1766971624,"localtime":"2025-12-29 03:27","last_updated_epoch":1766970900,"last_updated":"2025-12-29 03:15","temp_c":13.3,"temp_f":55.9,"is_day":0,"wind_mph":18.8,"wind_kph":30.2,"wind_degree":266,"wind_dir":"W","pressure_mb":1011,"pressure_in":29.85,"precip_mm":0.3,"precip_in":0.01,"humidity":88,"cloud":25,"feelslike_c":10.9,"feelslike_f":51.6,"windchill_c":15.7,"windchill_f":60.3,"heatindex_c":15.7,"heatindex_f":60.3,"dewpoint_c":8.4,"dewpoint_f":47.1,"vis_km":10,"vis_miles":6,"uv":0,"gust_mph":28.9,"gust_kph":46.5,"text":"Light rain","icon":"//cdn.weatherapi.com/weather/64x64/night/296.png","code":1183}