{"name":"Hadera","region":"Hefa","country":"Israel","lat":32.44,"lon":34.92,"tz_id":"Asia/Jerusalem","localtime_epoch":1662513995,"localtime":"2022-09-07 4:26","last_updated_epoch":1662513300,"last_updated":"2022-09-07 04:15","temp_c":25.5,"temp_f":77.9,"is_day":0,"wind_mph":4.7,"wind_kph":7.6,"wind_degree":258,"wind_dir":"WSW","pressure_mb":1008,"pressure_in":29.76,"precip_mm":0,"precip_in":0,"humidity":71,"cloud":65,"feelslike_c":27.2,"feelslike_f":81,"vis_km":10,"vis_miles":6,"uv":1,"gust_mph":6.9,"gust_kph":11.2,"text":"Cloudy","icon":"//cdn.weatherapi.com/weather/64x64/night/119.png","code":1006}