{"name":"Haifa","region":"Hefa","country":"Israel","lat":32.82,"lon":34.99,"tz_id":"Asia/Jerusalem","localtime_epoch":1718845016,"localtime":"2024-06-20 3:56","last_updated_epoch":1718844300,"last_updated":"2024-06-20 03:45","temp_c":23.9,"temp_f":75,"is_day":0,"wind_mph":7.4,"wind_kph":11.9,"wind_degree":345,"wind_dir":"NNW","pressure_mb":1008,"pressure_in":29.76,"precip_mm":0,"precip_in":0,"humidity":84,"cloud":3,"feelslike_c":26,"feelslike_f":78.7,"windchill_c":23.9,"windchill_f":75,"heatindex_c":26,"heatindex_f":78.7,"dewpoint_c":21,"dewpoint_f":69.8,"vis_km":10,"vis_miles":6,"uv":1,"gust_mph":12.6,"gust_kph":20.3,"text":"Clear","icon":"//cdn.weatherapi.com/weather/64x64/night/113.png","code":1000}