{"name":"Haifa","region":"Hefa","country":"Israel","lat":32.82,"lon":34.99,"tz_id":"Asia/Jerusalem","localtime_epoch":1707699196,"localtime":"2024-02-12 2:53","last_updated_epoch":1707698700,"last_updated":"2024-02-12 02:45","temp_c":15.2,"temp_f":59.3,"is_day":0,"wind_mph":10.3,"wind_kph":16.6,"wind_degree":113,"wind_dir":"ESE","pressure_mb":1020,"pressure_in":30.13,"precip_mm":0,"precip_in":0,"humidity":62,"cloud":32,"feelslike_c":15.2,"feelslike_f":59.3,"vis_km":10,"vis_miles":6,"uv":1,"gust_mph":19,"gust_kph":30.6,"text":"Partly Cloudy ","icon":"//cdn.weatherapi.com/weather/64x64/night/116.png","code":1003}