{"name":"Haifa","region":"Hefa","country":"Israel","lat":32.82,"lon":34.99,"tz_id":"Asia/Jerusalem","localtime_epoch":1684717415,"localtime":"2023-05-22 4:03","last_updated_epoch":1684717200,"last_updated":"2023-05-22 04:00","temp_c":23.8,"temp_f":74.8,"is_day":0,"wind_mph":14.3,"wind_kph":23,"wind_degree":131,"wind_dir":"SE","pressure_mb":1004,"pressure_in":29.64,"precip_mm":0,"precip_in":0,"humidity":47,"cloud":5,"feelslike_c":25,"feelslike_f":77,"vis_km":10,"vis_miles":6,"uv":1,"gust_mph":30,"gust_kph":48.2,"text":"Clear","icon":"//cdn.weatherapi.com/weather/64x64/night/113.png","code":1000}