{"name":"Holon","region":"Tel Aviv","country":"Israel","lat":32.0114,"lon":34.7722,"tz_id":"Asia/Jerusalem","localtime_epoch":1728177203,"localtime":"2024-10-06 04:13","last_updated_epoch":1728176400,"last_updated":"2024-10-06 04:00","temp_c":26.3,"temp_f":79.3,"is_day":0,"wind_mph":5.8,"wind_kph":9.4,"wind_degree":1,"wind_dir":"N","pressure_mb":1010,"pressure_in":29.83,"precip_mm":0,"precip_in":0,"humidity":74,"cloud":75,"feelslike_c":28.1,"feelslike_f":82.7,"windchill_c":24.5,"windchill_f":76.1,"heatindex_c":26.1,"heatindex_f":79,"dewpoint_c":18.6,"dewpoint_f":65.4,"vis_km":10,"vis_miles":6,"uv":1,"gust_mph":8.1,"gust_kph":13,"text":"Partly cloudy","icon":"//cdn.weatherapi.com/weather/64x64/night/116.png","code":1003}