{"name":"Jerusalem","region":"Yerushalayim","country":"Israel","lat":31.78,"lon":35.23,"tz_id":"Asia/Jerusalem","localtime_epoch":1733016308,"localtime":"2024-12-01 03:25","last_updated_epoch":1733015700,"last_updated":"2024-12-01 03:15","temp_c":10.1,"temp_f":50.2,"is_day":0,"wind_mph":2.2,"wind_kph":3.6,"wind_degree":292,"wind_dir":"WNW","pressure_mb":1021,"pressure_in":30.15,"precip_mm":0,"precip_in":0,"humidity":82,"cloud":0,"feelslike_c":10.4,"feelslike_f":50.6,"windchill_c":10.3,"windchill_f":50.6,"heatindex_c":10.1,"heatindex_f":50.1,"dewpoint_c":4.1,"dewpoint_f":39.4,"vis_km":10,"vis_miles":6,"uv":0,"gust_mph":4.7,"gust_kph":7.6,"text":"Clear","icon":"//cdn.weatherapi.com/weather/64x64/night/113.png","code":1000}