{"name":"Kfar Saba","region":"","country":"Israel","lat":32.19,"lon":34.96,"tz_id":"Asia/Jerusalem","localtime_epoch":1769131581,"localtime":"2026-01-23 03:26","last_updated_epoch":1769130900,"last_updated":"2026-01-23 03:15","temp_c":16.4,"temp_f":61.5,"is_day":0,"wind_mph":2.2,"wind_kph":3.6,"wind_degree":157,"wind_dir":"SSE","pressure_mb":1009,"pressure_in":29.8,"precip_mm":0.08,"precip_in":0,"humidity":63,"cloud":0,"feelslike_c":16.4,"feelslike_f":61.5,"windchill_c":13.1,"windchill_f":55.6,"heatindex_c":13.1,"heatindex_f":55.6,"dewpoint_c":3.3,"dewpoint_f":37.9,"vis_km":10,"vis_miles":6,"uv":0,"gust_mph":6.7,"gust_kph":10.8,"text":"Patchy rain nearby","icon":"//cdn.weatherapi.com/weather/64x64/night/176.png","code":1063}