{"name":"Kiryat Tivon","region":"Hefa","country":"Israel","lat":32.7239,"lon":35.1272,"tz_id":"Asia/Jerusalem","localtime_epoch":1755307532,"localtime":"2025-08-16 04:25","last_updated_epoch":1755306900,"last_updated":"2025-08-16 04:15","temp_c":24.8,"temp_f":76.7,"is_day":0,"wind_mph":5.4,"wind_kph":8.6,"wind_degree":291,"wind_dir":"WNW","pressure_mb":1007,"pressure_in":29.75,"precip_mm":0,"precip_in":0,"humidity":89,"cloud":46,"feelslike_c":27.4,"feelslike_f":81.3,"windchill_c":24.8,"windchill_f":76.7,"heatindex_c":27.4,"heatindex_f":81.3,"dewpoint_c":22.8,"dewpoint_f":73,"vis_km":10,"vis_miles":6,"uv":0,"gust_mph":7.9,"gust_kph":12.8,"text":"Partly Cloudy","icon":"//cdn.weatherapi.com/weather/64x64/night/116.png","code":1003}