{"name":"Qiryat Shmona","region":"HaZafon","country":"Israel","lat":33.21,"lon":35.57,"tz_id":"Asia/Jerusalem","localtime_epoch":1696727033,"localtime":"2023-10-08 4:03","last_updated_epoch":1696726800,"last_updated":"2023-10-08 04:00","temp_c":23,"temp_f":73.5,"is_day":0,"wind_mph":2.2,"wind_kph":3.6,"wind_degree":62,"wind_dir":"ENE","pressure_mb":1015,"pressure_in":29.97,"precip_mm":0,"precip_in":0,"humidity":72,"cloud":31,"feelslike_c":25,"feelslike_f":77.1,"vis_km":10,"vis_miles":6,"uv":1,"gust_mph":2.1,"gust_kph":3.4,"text":"Partly cloudy","icon":"//cdn.weatherapi.com/weather/64x64/night/116.png","code":1003}