{"name":"Kiryat-Amal","region":"Hefa","country":"Israel","lat":32.7067,"lon":35.1303,"tz_id":"Asia/Jerusalem","localtime_epoch":1757294446,"localtime":"2025-09-08 04:20","last_updated_epoch":1757294100,"last_updated":"2025-09-08 04:15","temp_c":22.9,"temp_f":73.3,"is_day":0,"wind_mph":2.9,"wind_kph":4.7,"wind_degree":207,"wind_dir":"SSW","pressure_mb":1009,"pressure_in":29.8,"precip_mm":0.02,"precip_in":0,"humidity":77,"cloud":81,"feelslike_c":25,"feelslike_f":77,"windchill_c":23,"windchill_f":73.3,"heatindex_c":25,"heatindex_f":77,"dewpoint_c":18.7,"dewpoint_f":65.6,"vis_km":10,"vis_miles":6,"uv":0,"gust_mph":4.6,"gust_kph":7.4,"text":"Patchy rain nearby","icon":"//cdn.weatherapi.com/weather/64x64/night/176.png","code":1063}