{"name":"Kiryat-Ata","region":"Hefa","country":"Israel","lat":32.8006,"lon":35.1064,"tz_id":"Asia/Jerusalem","localtime_epoch":1766971814,"localtime":"2025-12-29 03:30","last_updated_epoch":1766971800,"last_updated":"2025-12-29 03:30","temp_c":15.6,"temp_f":60.1,"is_day":0,"wind_mph":22.8,"wind_kph":36.7,"wind_degree":269,"wind_dir":"W","pressure_mb":1010,"pressure_in":29.82,"precip_mm":0.17,"precip_in":0.01,"humidity":64,"cloud":77,"feelslike_c":15.6,"feelslike_f":60.2,"windchill_c":15.6,"windchill_f":60.2,"heatindex_c":15.6,"heatindex_f":60.2,"dewpoint_c":8.9,"dewpoint_f":47.9,"vis_km":9,"vis_miles":5,"uv":0,"gust_mph":34.5,"gust_kph":55.6,"text":"Patchy rain nearby","icon":"//cdn.weatherapi.com/weather/64x64/night/176.png","code":1063}