{"name":"Qiryat Shmona","region":"HaZafon","country":"Israel","lat":33.21,"lon":35.57,"tz_id":"Asia/Jerusalem","localtime_epoch":1703292980,"localtime":"2023-12-23 2:56","last_updated_epoch":1703292300,"last_updated":"2023-12-23 02:45","temp_c":10.2,"temp_f":50.4,"is_day":0,"wind_mph":8.7,"wind_kph":14,"wind_degree":217,"wind_dir":"SW","pressure_mb":1010,"pressure_in":29.81,"precip_mm":1.32,"precip_in":0.05,"humidity":94,"cloud":100,"feelslike_c":8.3,"feelslike_f":47,"vis_km":10,"vis_miles":6,"uv":1,"gust_mph":17.5,"gust_kph":28.2,"text":"Light rain shower","icon":"//cdn.weatherapi.com/weather/64x64/night/353.png","code":1240}