{"name":"Qiryat Shmona","region":"HaZafon","country":"Israel","lat":33.21,"lon":35.57,"tz_id":"Asia/Jerusalem","localtime_epoch":1705971700,"localtime":"2024-01-23 3:01","last_updated_epoch":1705970700,"last_updated":"2024-01-23 02:45","temp_c":10.4,"temp_f":50.8,"is_day":0,"wind_mph":4.5,"wind_kph":7.2,"wind_degree":137,"wind_dir":"SE","pressure_mb":1016,"pressure_in":30,"precip_mm":0.37,"precip_in":0.01,"humidity":87,"cloud":52,"feelslike_c":9.7,"feelslike_f":49.5,"vis_km":10,"vis_miles":6,"uv":1,"gust_mph":7.1,"gust_kph":11.4,"text":"Light rain shower","icon":"//cdn.weatherapi.com/weather/64x64/night/353.png","code":1240}