{"name":"Qiryat Shmona","region":"HaZafon","country":"Israel","lat":33.2081,"lon":35.5686,"tz_id":"Asia/Jerusalem","localtime_epoch":1745717002,"localtime":"2025-04-27 04:23","last_updated_epoch":1745716500,"last_updated":"2025-04-27 04:15","temp_c":16.1,"temp_f":60.9,"is_day":0,"wind_mph":2.2,"wind_kph":3.6,"wind_degree":37,"wind_dir":"NE","pressure_mb":1013,"pressure_in":29.92,"precip_mm":0,"precip_in":0,"humidity":78,"cloud":4,"feelslike_c":16.1,"feelslike_f":60.9,"windchill_c":16.1,"windchill_f":60.9,"heatindex_c":16.1,"heatindex_f":60.9,"dewpoint_c":12.2,"dewpoint_f":53.9,"vis_km":10,"vis_miles":6,"uv":0,"gust_mph":6.7,"gust_kph":10.8,"text":"Clear","icon":"//cdn.weatherapi.com/weather/64x64/night/113.png","code":1000}