{"name":"Migdal","region":"HaZafon","country":"Israel","lat":32.83,"lon":35.5,"tz_id":"Asia/Jerusalem","localtime_epoch":1714611612,"localtime":"2024-05-02 4:00","last_updated_epoch":1714611600,"last_updated":"2024-05-02 04:00","temp_c":17.2,"temp_f":63,"is_day":0,"wind_mph":4,"wind_kph":6.5,"wind_degree":230,"wind_dir":"SW","pressure_mb":1009,"pressure_in":29.8,"precip_mm":0.02,"precip_in":0,"humidity":88,"cloud":95,"feelslike_c":17.2,"feelslike_f":63,"vis_km":10,"vis_miles":6,"uv":1,"gust_mph":7.8,"gust_kph":12.5,"text":"Patchy rain nearby","icon":"//cdn.weatherapi.com/weather/64x64/night/176.png","code":1063}