{"name":"Reut","region":"Bayern","country":"Germany","lat":48.32,"lon":12.93,"tz_id":"Europe/Berlin","localtime_epoch":1661650036,"localtime":"2022-08-28 3:27","last_updated_epoch":1661649300,"last_updated":"2022-08-28 03:15","temp_c":14.3,"temp_f":57.7,"is_day":0,"wind_mph":3.1,"wind_kph":5,"wind_degree":219,"wind_dir":"SW","pressure_mb":1014,"pressure_in":29.95,"precip_mm":0.2,"precip_in":0.01,"humidity":97,"cloud":85,"feelslike_c":14.6,"feelslike_f":58.3,"vis_km":9,"vis_miles":5,"uv":1,"gust_mph":6.5,"gust_kph":10.4,"text":"Patchy rain possible","icon":"//cdn.weatherapi.com/weather/64x64/night/176.png","code":1063}