{"name":"Reut","region":"Bayern","country":"Germany","lat":48.32,"lon":12.93,"tz_id":"Europe/Berlin","localtime_epoch":1663378292,"localtime":"2022-09-17 3:31","last_updated_epoch":1663378200,"last_updated":"2022-09-17 03:30","temp_c":9,"temp_f":48.2,"is_day":0,"wind_mph":7.6,"wind_kph":12.2,"wind_degree":251,"wind_dir":"WSW","pressure_mb":1011,"pressure_in":29.84,"precip_mm":0.2,"precip_in":0.01,"humidity":95,"cloud":77,"feelslike_c":7.1,"feelslike_f":44.8,"vis_km":9,"vis_miles":5,"uv":1,"gust_mph":12.3,"gust_kph":19.8,"text":"Patchy rain possible","icon":"//cdn.weatherapi.com/weather/64x64/night/176.png","code":1063}