{"name":"Reut","region":"Bayern","country":"Germany","lat":48.32,"lon":12.93,"tz_id":"Europe/Berlin","localtime_epoch":1665971705,"localtime":"2022-10-17 3:55","last_updated_epoch":1665971100,"last_updated":"2022-10-17 03:45","temp_c":11.1,"temp_f":52,"is_day":0,"wind_mph":3.1,"wind_kph":5,"wind_degree":91,"wind_dir":"E","pressure_mb":1024,"pressure_in":30.24,"precip_mm":0,"precip_in":0,"humidity":94,"cloud":5,"feelslike_c":11,"feelslike_f":51.8,"vis_km":10,"vis_miles":6,"uv":1,"gust_mph":6.5,"gust_kph":10.4,"text":"Clear","icon":"//cdn.weatherapi.com/weather/64x64/night/113.png","code":1000}