{"name":"Reut","region":"Bayern","country":"Germany","lat":48.3167,"lon":12.9333,"tz_id":"Europe/Berlin","localtime_epoch":1733880005,"localtime":"2024-12-11 02:20","last_updated_epoch":1733879700,"last_updated":"2024-12-11 02:15","temp_c":2.4,"temp_f":36.3,"is_day":0,"wind_mph":5.1,"wind_kph":8.3,"wind_degree":71,"wind_dir":"ENE","pressure_mb":1025,"pressure_in":30.27,"precip_mm":0,"precip_in":0,"humidity":87,"cloud":75,"feelslike_c":0,"feelslike_f":32,"windchill_c":-1.5,"windchill_f":29.3,"heatindex_c":1.1,"heatindex_f":34.1,"dewpoint_c":0.5,"dewpoint_f":32.9,"vis_km":10,"vis_miles":6,"uv":0,"gust_mph":7.4,"gust_kph":12,"text":"Partly cloudy","icon":"//cdn.weatherapi.com/weather/64x64/night/116.png","code":1003}