{"name":"Reut","region":"Bayern","country":"Germany","lat":48.32,"lon":12.93,"tz_id":"Europe/Berlin","localtime_epoch":1671498825,"localtime":"2022-12-20 2:13","last_updated_epoch":1671498000,"last_updated":"2022-12-20 02:00","temp_c":-5.1,"temp_f":22.8,"is_day":0,"wind_mph":3.1,"wind_kph":5,"wind_degree":121,"wind_dir":"ESE","pressure_mb":1028,"pressure_in":30.36,"precip_mm":0,"precip_in":0,"humidity":94,"cloud":10,"feelslike_c":-7.4,"feelslike_f":18.7,"vis_km":2,"vis_miles":1,"uv":1,"gust_mph":6.5,"gust_kph":10.4,"text":"Mist","icon":"//cdn.weatherapi.com/weather/64x64/night/143.png","code":1030}