{"name":"Reut","region":"Bayern","country":"Germany","lat":48.32,"lon":12.93,"tz_id":"Europe/Berlin","localtime_epoch":1673485905,"localtime":"2023-01-12 2:11","last_updated_epoch":1673485200,"last_updated":"2023-01-12 02:00","temp_c":4,"temp_f":39.2,"is_day":0,"wind_mph":5.6,"wind_kph":9,"wind_degree":150,"wind_dir":"SSE","pressure_mb":1022,"pressure_in":30.18,"precip_mm":0,"precip_in":0,"humidity":100,"cloud":75,"feelslike_c":0.2,"feelslike_f":32.4,"vis_km":10,"vis_miles":6,"uv":1,"gust_mph":17,"gust_kph":27.4,"text":"Light rain","icon":"//cdn.weatherapi.com/weather/64x64/night/296.png","code":1183}