{"name":"Nesher","region":"Hefa","country":"Israel","lat":32.765,"lon":35.05,"tz_id":"Asia/Jerusalem","localtime_epoch":1735348366,"localtime":"2024-12-28 03:12","last_updated_epoch":1735347600,"last_updated":"2024-12-28 03:00","temp_c":13,"temp_f":55.4,"is_day":0,"wind_mph":9.4,"wind_kph":15.1,"wind_degree":224,"wind_dir":"SW","pressure_mb":1016,"pressure_in":30,"precip_mm":1.35,"precip_in":0.05,"humidity":81,"cloud":87,"feelslike_c":11.6,"feelslike_f":52.8,"windchill_c":11.6,"windchill_f":52.8,"heatindex_c":13,"heatindex_f":55.4,"dewpoint_c":9.8,"dewpoint_f":49.6,"vis_km":10,"vis_miles":6,"uv":0,"gust_mph":15.1,"gust_kph":24.2,"text":"Light rain shower","icon":"//cdn.weatherapi.com/weather/64x64/night/353.png","code":1240}