{"name":"Nesher","region":"Hefa","country":"Israel","lat":32.77,"lon":35.05,"tz_id":"Asia/Jerusalem","localtime_epoch":1678496849,"localtime":"2023-03-11 3:07","last_updated_epoch":1678496400,"last_updated":"2023-03-11 03:00","temp_c":12.6,"temp_f":54.7,"is_day":0,"wind_mph":7.4,"wind_kph":11.9,"wind_degree":92,"wind_dir":"E","pressure_mb":1016,"pressure_in":29.99,"precip_mm":0,"precip_in":0,"humidity":57,"cloud":0,"feelslike_c":11.5,"feelslike_f":52.7,"vis_km":10,"vis_miles":6,"uv":1,"gust_mph":15.4,"gust_kph":24.8,"text":"Clear","icon":"//cdn.weatherapi.com/weather/64x64/night/113.png","code":1000}