{"name":"Nesher","region":"Hefa","country":"Israel","lat":32.77,"lon":35.05,"tz_id":"Asia/Jerusalem","localtime_epoch":1677287641,"localtime":"2023-02-25 3:14","last_updated_epoch":1677286800,"last_updated":"2023-02-25 03:00","temp_c":9.8,"temp_f":49.6,"is_day":0,"wind_mph":2.2,"wind_kph":3.6,"wind_degree":270,"wind_dir":"W","pressure_mb":1017,"pressure_in":30.03,"precip_mm":0,"precip_in":0,"humidity":86,"cloud":6,"feelslike_c":9.8,"feelslike_f":49.6,"vis_km":10,"vis_miles":6,"uv":1,"gust_mph":2.9,"gust_kph":4.7,"text":"Clear","icon":"//cdn.weatherapi.com/weather/64x64/night/113.png","code":1000}