{"name":"Ness Ziona","region":"HaMerkaz","country":"Israel","lat":31.9264,"lon":34.8033,"tz_id":"Asia/Jerusalem","localtime_epoch":1735348352,"localtime":"2024-12-28 03:12","last_updated_epoch":1735347600,"last_updated":"2024-12-28 03:00","temp_c":14.1,"temp_f":57.4,"is_day":0,"wind_mph":21,"wind_kph":33.8,"wind_degree":213,"wind_dir":"SSW","pressure_mb":1016,"pressure_in":30,"precip_mm":0.2,"precip_in":0.01,"humidity":44,"cloud":75,"feelslike_c":11.7,"feelslike_f":53.1,"windchill_c":11.5,"windchill_f":52.6,"heatindex_c":13.9,"heatindex_f":57,"dewpoint_c":7,"dewpoint_f":44.7,"vis_km":10,"vis_miles":6,"uv":0,"gust_mph":29.8,"gust_kph":47.9,"text":"Partly cloudy","icon":"//cdn.weatherapi.com/weather/64x64/night/116.png","code":1003}