{"name":"Netanya","region":"HaMerkaz","country":"Israel","lat":32.3336,"lon":34.8578,"tz_id":"Asia/Jerusalem","localtime_epoch":1735089216,"localtime":"2024-12-25 03:13","last_updated_epoch":1735088400,"last_updated":"2024-12-25 03:00","temp_c":14.4,"temp_f":58,"is_day":0,"wind_mph":5.1,"wind_kph":8.3,"wind_degree":101,"wind_dir":"ESE","pressure_mb":1017,"pressure_in":30.03,"precip_mm":0,"precip_in":0,"humidity":62,"cloud":0,"feelslike_c":14.2,"feelslike_f":57.5,"windchill_c":14.2,"windchill_f":57.5,"heatindex_c":14.5,"heatindex_f":58,"dewpoint_c":7.2,"dewpoint_f":45,"vis_km":10,"vis_miles":6,"uv":0,"gust_mph":9.8,"gust_kph":15.8,"text":"Clear","icon":"//cdn.weatherapi.com/weather/64x64/night/113.png","code":1000}