{"name":"Netivot","region":"HaDarom","country":"Israel","lat":31.42,"lon":34.58,"tz_id":"Asia/Jerusalem","localtime_epoch":1702688549,"localtime":"2023-12-16 3:02","last_updated_epoch":1702688400,"last_updated":"2023-12-16 03:00","temp_c":17.8,"temp_f":64,"is_day":0,"wind_mph":7.6,"wind_kph":12.2,"wind_degree":156,"wind_dir":"SSE","pressure_mb":1020,"pressure_in":30.11,"precip_mm":0,"precip_in":0,"humidity":50,"cloud":100,"feelslike_c":17.8,"feelslike_f":64,"vis_km":10,"vis_miles":6,"uv":1,"gust_mph":16,"gust_kph":25.7,"text":"Overcast","icon":"//cdn.weatherapi.com/weather/64x64/night/122.png","code":1009}