{"name":"Yefe Nof","region":"Yerushalayim","country":"Israel","lat":31.78,"lon":35.18,"tz_id":"Asia/Hebron","localtime_epoch":1668216412,"localtime":"2022-11-12 3:26","last_updated_epoch":1668215700,"last_updated":"2022-11-12 03:15","temp_c":17.1,"temp_f":62.8,"is_day":0,"wind_mph":2.7,"wind_kph":4.3,"wind_degree":350,"wind_dir":"N","pressure_mb":1017,"pressure_in":30.04,"precip_mm":0,"precip_in":0,"humidity":57,"cloud":4,"feelslike_c":17.1,"feelslike_f":62.8,"vis_km":10,"vis_miles":6,"uv":1,"gust_mph":5.1,"gust_kph":8.3,"text":"Clear","icon":"//cdn.weatherapi.com/weather/64x64/night/113.png","code":1000}