[{"name":"Yefe Nof","region":"Yerushalayim","country":"Israel","lat":31.78,"lon":35.18,"tz_id":"Asia/Jerusalem","localtime_epoch":1656191223,"localtime":"2022-06-26 0:07","last_updated_epoch":1656187200,"last_updated":"2022-06-25 23:00","temp_c":18.5,"temp_f":65.3,"is_day":0,"wind_mph":8.3,"wind_kph":13.3,"wind_degree":284,"wind_dir":"WNW","pressure_mb":1010,"pressure_in":29.81,"precip_mm":0,"precip_in":0,"humidity":74,"cloud":0,"feelslike_c":18.5,"feelslike_f":65.3,"vis_km":10,"vis_miles":6,"uv":1,"gust_mph":14.1,"gust_kph":22.7,"text":"Clear","icon":"//cdn.weatherapi.com/weather/64x64/night/113.png","code":1000}]