{"name":"Or Yehuda","region":"Tel Aviv","country":"Israel","lat":32.0311,"lon":34.8458,"tz_id":"Asia/Jerusalem","localtime_epoch":1732756847,"localtime":"2024-11-28 03:20","last_updated_epoch":1732756500,"last_updated":"2024-11-28 03:15","temp_c":14.3,"temp_f":57.7,"is_day":0,"wind_mph":5.1,"wind_kph":8.3,"wind_degree":170,"wind_dir":"S","pressure_mb":1022,"pressure_in":30.18,"precip_mm":0.08,"precip_in":0,"humidity":88,"cloud":75,"feelslike_c":14,"feelslike_f":57.2,"windchill_c":15.4,"windchill_f":59.7,"heatindex_c":15.4,"heatindex_f":59.7,"dewpoint_c":10.8,"dewpoint_f":51.5,"vis_km":10,"vis_miles":6,"uv":0,"gust_mph":8.1,"gust_kph":13,"text":"Light rain","icon":"//cdn.weatherapi.com/weather/64x64/night/296.png","code":1183}