{"name":"Paya Rahat","region":"Aceh","country":"Indonesia","lat":4.3985,"lon":98.1285,"tz_id":"Asia/Jakarta","localtime_epoch":1744593774,"localtime":"2025-04-14 08:22","last_updated_epoch":1744593300,"last_updated":"2025-04-14 08:15","temp_c":24.9,"temp_f":76.8,"is_day":1,"wind_mph":2.2,"wind_kph":3.6,"wind_degree":224,"wind_dir":"SW","pressure_mb":1011,"pressure_in":29.86,"precip_mm":0,"precip_in":0,"humidity":94,"cloud":88,"feelslike_c":27.9,"feelslike_f":82.2,"windchill_c":24.9,"windchill_f":76.8,"heatindex_c":27.9,"heatindex_f":82.2,"dewpoint_c":23.9,"dewpoint_f":74.9,"vis_km":10,"vis_miles":6,"uv":0.6,"gust_mph":2.7,"gust_kph":4.3,"text":"Overcast","icon":"//cdn.weatherapi.com/weather/64x64/day/122.png","code":1009}