{"name":"Paya Rahat","region":"Aceh","country":"Indonesia","lat":4.4,"lon":98.13,"tz_id":"Asia/Jakarta","localtime_epoch":1682730643,"localtime":"2023-04-29 8:10","last_updated_epoch":1682730000,"last_updated":"2023-04-29 08:00","temp_c":24,"temp_f":75.2,"is_day":1,"wind_mph":3.4,"wind_kph":5.4,"wind_degree":239,"wind_dir":"WSW","pressure_mb":1009,"pressure_in":29.78,"precip_mm":3.9,"precip_in":0.15,"humidity":94,"cloud":76,"feelslike_c":26.6,"feelslike_f":79.9,"vis_km":7,"vis_miles":4,"uv":5,"gust_mph":5.8,"gust_kph":9.4,"text":"Moderate or heavy rain shower","icon":"//cdn.weatherapi.com/weather/64x64/day/356.png","code":1243}