{"name":"Paya Rahat","region":"Aceh","country":"Indonesia","lat":4.4,"lon":98.13,"tz_id":"Asia/Jakarta","localtime_epoch":1688261400,"localtime":"2023-07-02 8:30","last_updated_epoch":1688261400,"last_updated":"2023-07-02 08:30","temp_c":23.1,"temp_f":73.6,"is_day":1,"wind_mph":4,"wind_kph":6.5,"wind_degree":198,"wind_dir":"SSW","pressure_mb":1010,"pressure_in":29.83,"precip_mm":0,"precip_in":0,"humidity":92,"cloud":19,"feelslike_c":25.4,"feelslike_f":77.7,"vis_km":10,"vis_miles":6,"uv":6,"gust_mph":7.4,"gust_kph":11.9,"text":"Sunny","icon":"//cdn.weatherapi.com/weather/64x64/day/113.png","code":1000}