{"name":"Rahat Aghawat","region":"Ninawa","country":"Iraq","lat":36.4589,"lon":43.2169,"tz_id":"Asia/Baghdad","localtime_epoch":1765071261,"localtime":"2025-12-07 04:34","last_updated_epoch":1765071000,"last_updated":"2025-12-07 04:30","temp_c":16.4,"temp_f":61.4,"is_day":0,"wind_mph":10.3,"wind_kph":16.6,"wind_degree":84,"wind_dir":"E","pressure_mb":1018,"pressure_in":30.06,"precip_mm":0,"precip_in":0,"humidity":40,"cloud":62,"feelslike_c":16.4,"feelslike_f":61.4,"windchill_c":16.4,"windchill_f":61.4,"heatindex_c":16.4,"heatindex_f":61.4,"dewpoint_c":2.9,"dewpoint_f":37.1,"vis_km":10,"vis_miles":6,"uv":0,"gust_mph":20.5,"gust_kph":32.9,"text":"Partly Cloudy","icon":"//cdn.weatherapi.com/weather/64x64/night/116.png","code":1003}