{"name":"Rahat Salamat","region":"Batha","country":"Chad","lat":13.1667,"lon":17.4167,"tz_id":"Africa/Ndjamena","localtime_epoch":1772157394,"localtime":"2026-02-27 02:56","last_updated_epoch":1772156700,"last_updated":"2026-02-27 02:45","temp_c":19.1,"temp_f":66.4,"is_day":0,"wind_mph":12.3,"wind_kph":19.8,"wind_degree":23,"wind_dir":"NNE","pressure_mb":1013,"pressure_in":29.91,"precip_mm":0,"precip_in":0,"humidity":13,"cloud":0,"feelslike_c":19.1,"feelslike_f":66.4,"windchill_c":19.1,"windchill_f":66.4,"heatindex_c":19.1,"heatindex_f":66.4,"dewpoint_c":-10,"dewpoint_f":13.9,"vis_km":10,"vis_miles":6,"uv":0,"gust_mph":24,"gust_kph":38.6,"text":"Clear","icon":"//cdn.weatherapi.com/weather/64x64/night/113.png","code":1000}