{"name":"Rahat Salamat","region":"Batha","country":"Chad","lat":13.17,"lon":17.42,"tz_id":"Africa/Ndjamena","localtime_epoch":1713229419,"localtime":"2024-04-16 2:03","last_updated_epoch":1713229200,"last_updated":"2024-04-16 02:00","temp_c":31.3,"temp_f":88.3,"is_day":0,"wind_mph":10.3,"wind_kph":16.6,"wind_degree":45,"wind_dir":"NE","pressure_mb":1005,"pressure_in":29.68,"precip_mm":0,"precip_in":0,"humidity":10,"cloud":2,"feelslike_c":29,"feelslike_f":84.2,"vis_km":10,"vis_miles":6,"uv":1,"gust_mph":21.6,"gust_kph":34.8,"text":"Clear","icon":"//cdn.weatherapi.com/weather/64x64/night/113.png","code":1000}