{"name":"Ramat Gan","region":"Tel Aviv","country":"Israel","lat":32.0806,"lon":34.8142,"tz_id":"Asia/Jerusalem","localtime_epoch":1773280814,"localtime":"2026-03-12 04:00","last_updated_epoch":1773280800,"last_updated":"2026-03-12 04:00","temp_c":13.1,"temp_f":55.6,"is_day":0,"wind_mph":6,"wind_kph":9.7,"wind_degree":168,"wind_dir":"SSE","pressure_mb":1015,"pressure_in":29.97,"precip_mm":0,"precip_in":0,"humidity":58,"cloud":0,"feelslike_c":12.4,"feelslike_f":54.3,"windchill_c":13.2,"windchill_f":55.8,"heatindex_c":13.8,"heatindex_f":56.8,"dewpoint_c":7.1,"dewpoint_f":44.8,"vis_km":10,"vis_miles":6,"uv":0,"gust_mph":11.3,"gust_kph":18.2,"text":"Clear","icon":"//cdn.weatherapi.com/weather/64x64/night/113.png","code":1000}