{"name":"Safed","region":"HaZafon","country":"Israel","lat":32.97,"lon":35.49,"tz_id":"Asia/Jerusalem","localtime_epoch":1682730795,"localtime":"2023-04-29 4:13","last_updated_epoch":1682730000,"last_updated":"2023-04-29 04:00","temp_c":14.6,"temp_f":58.3,"is_day":0,"wind_mph":6.3,"wind_kph":10.1,"wind_degree":219,"wind_dir":"SW","pressure_mb":1009,"pressure_in":29.81,"precip_mm":0.1,"precip_in":0,"humidity":72,"cloud":78,"feelslike_c":14.1,"feelslike_f":57.4,"vis_km":10,"vis_miles":6,"uv":1,"gust_mph":9.6,"gust_kph":15.5,"text":"Patchy rain possible","icon":"//cdn.weatherapi.com/weather/64x64/night/176.png","code":1063}