{"name":"Shafa `Amr","region":"HaZafon","country":"Israel","lat":32.8,"lon":35.17,"tz_id":"Asia/Jerusalem","localtime_epoch":1682644591,"localtime":"2023-04-28 4:16","last_updated_epoch":1682644500,"last_updated":"2023-04-28 04:15","temp_c":15,"temp_f":59,"is_day":0,"wind_mph":3.6,"wind_kph":5.8,"wind_degree":244,"wind_dir":"WSW","pressure_mb":1009,"pressure_in":29.8,"precip_mm":0,"precip_in":0,"humidity":75,"cloud":9,"feelslike_c":15.3,"feelslike_f":59.5,"vis_km":10,"vis_miles":6,"uv":1,"gust_mph":6.9,"gust_kph":11.2,"text":"Clear","icon":"//cdn.weatherapi.com/weather/64x64/night/113.png","code":1000}