{"name":"Shafa `Amr","region":"HaZafon","country":"Israel","lat":32.8,"lon":35.17,"tz_id":"Asia/Jerusalem","localtime_epoch":1701133759,"localtime":"2023-11-28 3:09","last_updated_epoch":1701133200,"last_updated":"2023-11-28 03:00","temp_c":15.4,"temp_f":59.8,"is_day":0,"wind_mph":11.6,"wind_kph":18.7,"wind_degree":305,"wind_dir":"NW","pressure_mb":1020,"pressure_in":30.11,"precip_mm":0.09,"precip_in":0,"humidity":60,"cloud":79,"feelslike_c":15.4,"feelslike_f":59.8,"vis_km":10,"vis_miles":6,"uv":1,"gust_mph":16.8,"gust_kph":27.1,"text":"Patchy rain possible","icon":"//cdn.weatherapi.com/weather/64x64/night/176.png","code":1063}