{"name":"Tayibe","region":"HaMerkaz","country":"Israel","lat":32.2647,"lon":35.0081,"tz_id":"Asia/Jerusalem","localtime_epoch":1754098380,"localtime":"2025-08-02 04:33","last_updated_epoch":1754098200,"last_updated":"2025-08-02 04:30","temp_c":26.1,"temp_f":79,"is_day":0,"wind_mph":6.9,"wind_kph":11.2,"wind_degree":208,"wind_dir":"SSW","pressure_mb":1005,"pressure_in":29.68,"precip_mm":0.02,"precip_in":0,"humidity":74,"cloud":25,"feelslike_c":28,"feelslike_f":82.3,"windchill_c":25.7,"windchill_f":78.3,"heatindex_c":27.5,"heatindex_f":81.4,"dewpoint_c":20,"dewpoint_f":67.9,"vis_km":10,"vis_miles":6,"uv":0,"gust_mph":10.5,"gust_kph":16.9,"text":"Patchy rain nearby","icon":"//cdn.weatherapi.com/weather/64x64/night/176.png","code":1063}