{"name":"Tiberias","region":"HaZafon","country":"Israel","lat":32.8,"lon":35.53,"tz_id":"Asia/Jerusalem","localtime_epoch":1684804638,"localtime":"2023-05-23 4:17","last_updated_epoch":1684804500,"last_updated":"2023-05-23 04:15","temp_c":16.3,"temp_f":61.3,"is_day":0,"wind_mph":2.5,"wind_kph":4,"wind_degree":222,"wind_dir":"SW","pressure_mb":1012,"pressure_in":29.88,"precip_mm":0,"precip_in":0,"humidity":84,"cloud":12,"feelslike_c":16.3,"feelslike_f":61.3,"vis_km":10,"vis_miles":6,"uv":1,"gust_mph":5.1,"gust_kph":8.3,"text":"Clear","icon":"//cdn.weatherapi.com/weather/64x64/night/113.png","code":1000}