{"name":"Tirat Carmel","region":"Hefa","country":"Israel","lat":32.76,"lon":34.97,"tz_id":"Asia/Jerusalem","localtime_epoch":1673746141,"localtime":"2023-01-15 3:29","last_updated_epoch":1673745300,"last_updated":"2023-01-15 03:15","temp_c":11.7,"temp_f":53.1,"is_day":0,"wind_mph":13.9,"wind_kph":22.3,"wind_degree":145,"wind_dir":"SE","pressure_mb":1018,"pressure_in":30.06,"precip_mm":0.3,"precip_in":0.01,"humidity":81,"cloud":100,"feelslike_c":9.3,"feelslike_f":48.7,"vis_km":10,"vis_miles":6,"uv":1,"gust_mph":24.4,"gust_kph":39.2,"text":"Light rain shower","icon":"//cdn.weatherapi.com/weather/64x64/night/353.png","code":1240}