{"name":"Tira","region":"Hefa","country":"Israel","lat":32.76,"lon":34.97,"tz_id":"Asia/Jerusalem","localtime_epoch":1679275448,"localtime":"2023-03-20 3:24","last_updated_epoch":1679274900,"last_updated":"2023-03-20 03:15","temp_c":14,"temp_f":57.2,"is_day":0,"wind_mph":15.4,"wind_kph":24.8,"wind_degree":287,"wind_dir":"WNW","pressure_mb":1010,"pressure_in":29.82,"precip_mm":0.9,"precip_in":0.04,"humidity":79,"cloud":90,"feelslike_c":12.1,"feelslike_f":53.8,"vis_km":10,"vis_miles":6,"uv":1,"gust_mph":22.4,"gust_kph":36,"text":"Light rain shower","icon":"//cdn.weatherapi.com/weather/64x64/night/353.png","code":1240}