{"name":"Tira","region":"HaMerkaz","country":"Israel","lat":32.0142,"lon":34.9325,"tz_id":"Asia/Jerusalem","localtime_epoch":1772762652,"localtime":"2026-03-06 04:04","last_updated_epoch":1772762400,"last_updated":"2026-03-06 04:00","temp_c":8.1,"temp_f":46.6,"is_day":0,"wind_mph":3.4,"wind_kph":5.4,"wind_degree":60,"wind_dir":"ENE","pressure_mb":1020,"pressure_in":30.12,"precip_mm":0,"precip_in":0,"humidity":71,"cloud":0,"feelslike_c":7.5,"feelslike_f":45.4,"windchill_c":9,"windchill_f":48.2,"heatindex_c":9.4,"heatindex_f":49,"dewpoint_c":2.8,"dewpoint_f":37,"vis_km":10,"vis_miles":6,"uv":1,"gust_mph":7,"gust_kph":11.3,"text":"Clear","icon":"//cdn.weatherapi.com/weather/64x64/night/113.png","code":1000}