{"name":"Tirat Carmel","region":"Hefa","country":"Israel","lat":32.76,"lon":34.97,"tz_id":"Asia/Jerusalem","localtime_epoch":1678670522,"localtime":"2023-03-13 3:22","last_updated_epoch":1678670100,"last_updated":"2023-03-13 03:15","temp_c":15.4,"temp_f":59.7,"is_day":0,"wind_mph":4.3,"wind_kph":6.8,"wind_degree":183,"wind_dir":"S","pressure_mb":1008,"pressure_in":29.78,"precip_mm":0,"precip_in":0,"humidity":64,"cloud":95,"feelslike_c":15.4,"feelslike_f":59.7,"vis_km":10,"vis_miles":6,"uv":1,"gust_mph":8.7,"gust_kph":14,"text":"Overcast","icon":"//cdn.weatherapi.com/weather/64x64/night/122.png","code":1009}